{
  "services": {
    "get_album": { "service": "mdi:album"},
    "get_album_tracks": { "service": "mdi:album"},
    "get_artist": { "service": "mdi:account-music"},
    "get_artist_tracks": { "service": "mdi:account-music"},
    "get_playlist": { "service": "mdi:playlist-music"},
    "get_playlist_tracks": { "service": "mdi:playlist-music"},
    "get_podcast": { "service": "mdi:podcast"},
    "get_podcast_episodes": { "service": "mdi:podcast"},
    "get_queue_items": { "service": "mdi:playlist-music" },
    "move_queue_item_down": { "service": "mdi:arrow-down" },
    "move_queue_item_next": { "service": "mdi:arrow-collapse-up" },
    "move_queue_item_up": { "service": "mdi:arrow-up" },
    "play_queue_item": { "service": "mdi:play" },
    "remove_queue_item": { "service": "mdi:close" },
    "send_command": { "service": "mdi:send" },
    "unfavorite_current_item": { "service": "mdi:heart-remove" },
    "get_recommendations": { "service": "mdi:creation"},
    "get_group_volume": { "service": "mdi:speaker-multiple"},
    "set_group_volume": { "service": "mdi:speaker-multiple"},
    "clear_queue_from_here": { "service": "mdi:playlist-remove"},
    "remove_playlist_tracks": { "service": "mdi:playlist-remove"}
  }
}
